brizz/__init__.py
brizz/py.typed
brizz/_internal/__init__.py
brizz/_internal/config.py
brizz/_internal/constants.py
brizz/_internal/exceptions.py
brizz/_internal/models.py
brizz/_internal/sdk.py
brizz/_internal/semantic_conventions.py
brizz/_internal/session.py
brizz/_internal/version.py
brizz/_internal/instrumentation/__init__.py
brizz/_internal/instrumentation/registry.py
brizz/_internal/log/__init__.py
brizz/_internal/log/logging.py
brizz/_internal/log/processors/__init__.py
brizz/_internal/log/processors/log_processor.py
brizz/_internal/masking/__init__.py
brizz/_internal/masking/patterns.py
brizz/_internal/masking/utils.py
brizz/_internal/metric/__init__.py
brizz/_internal/metric/metrics.py
brizz/_internal/trace/__init__.py
brizz/_internal/trace/tracing.py
brizz/_internal/trace/processors/__init__.py
brizz/_internal/trace/processors/span_processor.py
brizz-0.1.10.dist-info/METADATA
brizz-0.1.10.dist-info/WHEEL
brizz-0.1.10.dist-info/licenses/LICENSE
brizz-0.1.10.dist-info/RECORD
