Metadata-Version: 2.4
Name: brizz
Version: 0.1.10
Summary: Official Python SDK for Brizz platform
Author-email: Brizz Team <contact@brizz.ai>
License: Apache-2.0
License-File: LICENSE
Keywords: ai,api,brizz,brizzai,instrumentation,llm,monitoring,observability,opentelemetry,sdk,telemetry,tracing
Classifier: Intended Audience :: Developers
Classifier: License :: OSI Approved :: Apache Software License
Classifier: Programming Language :: Python :: 3
Classifier: Programming Language :: Python :: 3.10
Classifier: Programming Language :: Python :: 3.11
Classifier: Programming Language :: Python :: 3.12
Classifier: Programming Language :: Python :: 3.13
Classifier: Topic :: Software Development :: Libraries :: Python Modules
Requires-Python: <3.14,>=3.10
Requires-Dist: httpx>=0.25.0
Requires-Dist: openinference-instrumentation-openai>=0.1.39
Requires-Dist: opentelemetry-api<1.40.0,>=1.39.0
Requires-Dist: opentelemetry-exporter-otlp-proto-http<1.40.0,>=1.39.0
Requires-Dist: opentelemetry-instrumentation-aiohttp-client>=0.55b1
Requires-Dist: opentelemetry-instrumentation-alephalpha>=0.44.0
Requires-Dist: opentelemetry-instrumentation-anthropic<0.48.0,>=0.30.0
Requires-Dist: opentelemetry-instrumentation-bedrock>=0.30.0
Requires-Dist: opentelemetry-instrumentation-chromadb>=0.44.0
Requires-Dist: opentelemetry-instrumentation-cohere>=0.30.0
Requires-Dist: opentelemetry-instrumentation-crewai>=0.44.0
Requires-Dist: opentelemetry-instrumentation-google-generativeai>=0.44.0
Requires-Dist: opentelemetry-instrumentation-groq>=0.44.0
Requires-Dist: opentelemetry-instrumentation-httpx>=0.55b1
Requires-Dist: opentelemetry-instrumentation-lancedb>=0.44.0
Requires-Dist: opentelemetry-instrumentation-langchain<0.48.0,>=0.30.0
Requires-Dist: opentelemetry-instrumentation-llamaindex>=0.30.0
Requires-Dist: opentelemetry-instrumentation-marqo>=0.44.0
Requires-Dist: opentelemetry-instrumentation-milvus>=0.44.0
Requires-Dist: opentelemetry-instrumentation-mistralai>=0.44.0
Requires-Dist: opentelemetry-instrumentation-ollama>=0.44.0
Requires-Dist: opentelemetry-instrumentation-openai-agents>=0.44.0
Requires-Dist: opentelemetry-instrumentation-pinecone>=0.44.0
Requires-Dist: opentelemetry-instrumentation-qdrant>=0.44.0
Requires-Dist: opentelemetry-instrumentation-redis>=0.55b1
Requires-Dist: opentelemetry-instrumentation-replicate>=0.44.0
Requires-Dist: opentelemetry-instrumentation-requests>=0.55b1
Requires-Dist: opentelemetry-instrumentation-sagemaker>=0.44.0
Requires-Dist: opentelemetry-instrumentation-sqlalchemy>=0.55b1
Requires-Dist: opentelemetry-instrumentation-threading>=0.55b1
Requires-Dist: opentelemetry-instrumentation-together>=0.44.0
Requires-Dist: opentelemetry-instrumentation-transformers>=0.44.0
Requires-Dist: opentelemetry-instrumentation-urllib3>=0.55b1
Requires-Dist: opentelemetry-instrumentation-urllib>=0.55b1
Requires-Dist: opentelemetry-instrumentation-vertexai>=0.30.0
Requires-Dist: opentelemetry-instrumentation-watsonx>=0.44.0
Requires-Dist: opentelemetry-instrumentation-weaviate>=0.44.0
Requires-Dist: opentelemetry-instrumentation>=0.60b0
Requires-Dist: opentelemetry-sdk<1.40.0,>=1.39.0
Requires-Dist: opentelemetry-semantic-conventions-ai>=0.4.0
Requires-Dist: opentelemetry-semantic-conventions>=0.60b0
Requires-Dist: pydantic>=2.0.0
